dask_kubernetes/__init__.py
dask_kubernetes/_version.py
dask_kubernetes/config.py
dask_kubernetes/conftest.py
dask_kubernetes/constants.py
dask_kubernetes/exceptions.py
dask_kubernetes/kubernetes.yaml
dask_kubernetes/cli/__init__.py
dask_kubernetes/cli/cli.py
dask_kubernetes/operator/__init__.py
dask_kubernetes/operator/_objects.py
dask_kubernetes/operator/networking.py
dask_kubernetes/operator/validation.py
dask_kubernetes/operator/controller/__init__.py
dask_kubernetes/operator/controller/controller.py
dask_kubernetes/operator/controller/plugins/__init__.py
dask_kubernetes/operator/controller/plugins/noop/__init__.py
dask_kubernetes/operator/controller/plugins/noop/noop.py
dask_kubernetes/operator/controller/tests/test_controller.py
dask_kubernetes/operator/controller/tests/resources/failedjob.yaml
dask_kubernetes/operator/controller/tests/resources/simplecluster.yaml
dask_kubernetes/operator/controller/tests/resources/simplejob.yaml
dask_kubernetes/operator/controller/tests/resources/simpleworkergroup.yaml
dask_kubernetes/operator/customresources/daskautoscaler.patch.yaml
dask_kubernetes/operator/customresources/daskautoscaler.yaml
dask_kubernetes/operator/customresources/daskcluster.patch.yaml
dask_kubernetes/operator/customresources/daskcluster.yaml
dask_kubernetes/operator/customresources/daskjob.patch.yaml
dask_kubernetes/operator/customresources/daskjob.yaml
dask_kubernetes/operator/customresources/daskworkergroup.patch.yaml
dask_kubernetes/operator/customresources/daskworkergroup.yaml
dask_kubernetes/operator/customresources/templates.yaml
dask_kubernetes/operator/deployment/Dockerfile
dask_kubernetes/operator/deployment/helm/README.md
dask_kubernetes/operator/deployment/helm/chartpress.yaml
dask_kubernetes/operator/deployment/helm/dask-kubernetes-operator/.helmignore
dask_kubernetes/operator/deployment/helm/dask-kubernetes-operator/Chart.yaml
dask_kubernetes/operator/deployment/helm/dask-kubernetes-operator/README.md
dask_kubernetes-2025.4.3.dist-info/METADATA
dask_kubernetes-2025.4.3.dist-info/WHEEL
dask_kubernetes-2025.4.3.dist-info/entry_points.txt
dask_kubernetes-2025.4.3.dist-info/licenses/LICENSE
dask_kubernetes-2025.4.3.dist-info/RECORD
