Metadata-Version: 2.4
Name: dask-kubernetes
Version: 2025.4.3
Summary: Native Kubernetes integration for Dask
Project-URL: Homepage, https://github.com/dask/dask-kubernetes
Maintainer: Jacob Tomlinson
License: BSD 3-Clause License
License-File: LICENSE
Keywords: dask,distributed,kubernetes
Requires-Python: >=3.10
Requires-Dist: dask>=2022.08.1
Requires-Dist: distributed>=2022.08.1
Requires-Dist: kopf>=1.35.3
Requires-Dist: kr8s==0.20.*
Requires-Dist: kubernetes-asyncio>=12.0.1
Requires-Dist: kubernetes>=12.0.1
Requires-Dist: pykube-ng>=22.9.0
Requires-Dist: rich>=12.5.1
